<?xml version="1.0"?>
<!DOCTYPE hibernate-mapping PUBLIC "-//Hibernate/Hibernate Mapping DTD 3.0//EN"
"http://www.hibernate.org/dtd/hibernate-mapping-3.0.dtd">
<!-- Generated 24-abr-2018 21:28:22 by Hibernate Tools 4.3.1 -->
<hibernate-mapping>
    <class name="gestionhotel.zapto.org.gestionhotelcliente.modelos.pojos.DetallesReserva" table="detalles_reserva" catalog="gestionhotel" optimistic-lock="version">
        <id name="idDetallesReserva" type="java.lang.Integer">
            <column name="id_detalles_reserva" />
            <generator class="identity" />
        </id>
        <many-to-one name="habitacion" class="gestionhotel.zapto.org.gestionhotelcliente.modelos.pojos.Habitacion" fetch="select">
            <column name="id_habitacion" />
        </many-to-one>
        <many-to-one name="reserva" class="gestionhotel.zapto.org.gestionhotelcliente.modelos.pojos.Reserva" fetch="select">
            <column name="cod_reserva" />
        </many-to-one>
        <property name="nombreReserva" type="string">
            <column name="nombre_reserva" length="40" />
        </property>
        <property name="cantidadHuespedes" type="java.lang.Integer">
            <column name="cantidad_huespedes" />
        </property>
        <property name="fechaEntradaPrevista" type="date">
            <column name="fecha_entrada_prevista" length="10" />
        </property>
        <property name="fechaSalidaPrevista" type="date">
            <column name="fecha_salida_prevista" length="10" />
        </property>
        <property name="fechaEntrada" type="date">
            <column name="fecha_entrada" length="10" />
        </property>
        <property name="fechaSalida" type="date">
            <column name="fecha_salida" length="10" />
        </property>
        <property name="pension" type="string">
            <column name="pension" length="40" />
        </property>
        <property name="tipoCama" type="string">
            <column name="tipo_cama" length="40" />
        </property>
        <set name="estadoHabitacions" table="estado_habitacion" inverse="true" lazy="true" fetch="select">
            <key>
                <column name="id_alojamiento" />
            </key>
            <one-to-many class="gestionhotel.zapto.org.gestionhotelcliente.modelos.pojos.EstadoHabitacion" />
        </set>
        <set name="huespedHabitacions" table="huesped_habitacion" inverse="true" lazy="true" fetch="select">
            <key>
                <column name="id_detalles_reservas" not-null="true" />
            </key>
            <one-to-many class="gestionhotel.zapto.org.gestionhotelcliente.modelos.pojos.HuespedHabitacion" />
        </set>
    </class>
</hibernate-mapping>
